abdalelah_calculator-0.1.0.dist-info/licenses/LICENSE
calculator/__init__.py
calculator/advanced.py
calculator/core.py
abdalelah_calculator-0.1.0.dist-info/METADATA
abdalelah_calculator-0.1.0.dist-info/WHEEL
abdalelah_calculator-0.1.0.dist-info/top_level.txt
abdalelah_calculator-0.1.0.dist-info/RECORD
