Metadata-Version: 2.4
Name: abdalelah-calculator
Version: 0.1.0
Summary: آلة حاسبة احترافية ببايثون
Author-email: abdalelah-calculator <alzaydybdalalh1@gmail.com>
License: MIT License
Project-URL: Homepage, https://pypi.org/project/abdalelah/
Requires-Python: >=3.8
License-File: LICENSE
Dynamic: license-file
